README.md
fdprogress.py
setup.py
fdprogress.egg-info/PKG-INFO
fdprogress.egg-info/SOURCES.txt
fdprogress.egg-info/dependency_links.txt
fdprogress.egg-info/entry_points.txt
fdprogress.egg-info/top_level.txt