Metadata-Version: 2.1
Name: fdprogress
Version: 0.2.0
Summary: Monitor file descriptor progress on Linux
Home-page: https://github.com/JonathonReinhart/fdprogress
Author: Jonathon Reinhart
Author-email: jonathon.reinhart@gmail.com
License: MIT
Keywords: file descriptor watch
Platform: UNKNOWN
Classifier: Development Status :: 4 - Beta
Classifier: Environment :: Console
Classifier: Intended Audience :: Developers
Classifier: License :: OSI Approved :: MIT License
Classifier: Natural Language :: English
Classifier: Operating System :: POSIX :: Linux
Classifier: Topic :: System :: Monitoring
